fcn_f0/data/fcn_993/__init__.py
fcn_f0/data/fcn_993/weights.h5
fcn_f0_data_fcn_993-1.0.0.dist-info/LICENSE
fcn_f0_data_fcn_993-1.0.0.dist-info/METADATA
fcn_f0_data_fcn_993-1.0.0.dist-info/WHEEL
fcn_f0_data_fcn_993-1.0.0.dist-info/top_level.txt
fcn_f0_data_fcn_993-1.0.0.dist-info/RECORD
